g85/LICENSE.md
g85/README.md
g85/__init__.py
g85/main.py
g85/read.py
g85/write.py
g85-0.7.dist-info/METADATA
g85-0.7.dist-info/WHEEL
g85-0.7.dist-info/licenses/LICENSE.md
g85-0.7.dist-info/RECORD
