Metadata-Version: 2.3
Name: g85
Version: 0.7
Summary: G85 wafer map reader / writer
Author-email: Jan Petykiewicz <jan@mpxd.net>
License: GNU General Public License
License-File: LICENSE.md
Keywords: CAD,EDA,G85,IC,design,electronics,map,mask,photonics,wafer,wmap
Classifier: Development Status :: 4 - Beta
Classifier: Intended Audience :: Developers
Classifier: Intended Audience :: Information Technology
Classifier: Intended Audience :: Manufacturing
Classifier: Intended Audience :: Science/Research
Classifier: License :: OSI Approved :: GNU General Public License v3 (GPLv3)
Classifier: Programming Language :: Python :: 3
Classifier: Topic :: Scientific/Engineering :: Electronic Design Automation (EDA)
Requires-Python: >=3.10
